topsis_harshit_102303276/__init__.py
topsis_harshit_102303276-0.1.0.dist-info/WHEEL
topsis_harshit_102303276-0.1.0.dist-info/entry_points.txt
topsis_harshit_102303276-0.1.0.dist-info/METADATA
topsis_harshit_102303276-0.1.0.dist-info/RECORD
