Metadata-Version: 2.3
Name: topsis_harshit_102303276
Version: 0.1.0
Summary: Implementation of the TOPSIS Algorithm
Author: HarshitCodes16
Author-email: HarshitCodes16 <hkatyal_be23@thapar.edu>
Requires-Python: >=3.13
